{
    "configurations": [
        {
            "name": "Linux",
            "includePath": [
                "${workspaceFolder}/**",
                "${workspaceFolder}/src",
                "/usr/include",
                "/usr/local/include",
                "/usr/lib/gcc/x86_64-redhat-linux/14/include"
            ],
            "defines": [],
            "compilerPath": "/usr/bin/gcc",
            "cStandard": "c11",
            "cppStandard": "c++17",
            "intelliSenseMode": "linux-gcc-x64",
            "browse": {
                "path": [
                    "${workspaceFolder}/**",
                    "/usr/include",
                    "/usr/local/include",
                    "/usr/lib/gcc/x86_64-redhat-linux/14/include"
                ],
                "limitSymbolsToIncludedHeaders": true
            }
        }
    ],
    "version": 4
}